Metadata-Version: 2.1
Name: jhOMR
Version: 0.0.2
Summary: OMR format to be used in KUET
Home-page: UNKNOWN
Author: Md Nur Kutubul Alam
Author-email: alamjhilam@gmail.com
License: UNKNOWN
Platform: UNKNOWN
